ansiblespawner/__init__.py
ansiblespawner/_version.py
ansiblespawner/ansiblespawner.py
ansiblespawner-0.0.1.dist-info/LICENSE
ansiblespawner-0.0.1.dist-info/METADATA
ansiblespawner-0.0.1.dist-info/WHEEL
ansiblespawner-0.0.1.dist-info/entry_points.txt
ansiblespawner-0.0.1.dist-info/top_level.txt
ansiblespawner-0.0.1.dist-info/RECORD
